error_summary.py
rf_error_summary-1.0.3.dist-info/METADATA
rf_error_summary-1.0.3.dist-info/WHEEL
rf_error_summary-1.0.3.dist-info/entry_points.txt
rf_error_summary-1.0.3.dist-info/top_level.txt
rf_error_summary-1.0.3.dist-info/RECORD
