Metadata-Version: 2.1
Name: rf-error-summary
Version: 1.0.3
Summary: A utility to process robot framework junit XML and then create unique error report with error count and latest test name for easy and quick issue analysis.
Home-page: UNKNOWN
Author: Chandan Mishra
Author-email: testautomasi@gmail.com
License: UNKNOWN
Platform: UNKNOWN
Classifier: Programming Language :: Python :: 3
Classifier: License :: OSI Approved :: MIT License
Classifier: Operating System :: OS Independent
Requires-Python: >=3.6
